{
    "hylc": {
        "enabled": true,
        "type": 0 // -1 analytic, 0 knit, 1 knit, 2 woven, 3 woven
        //"a0": 0,
        //"a1": 0,
        //"b0": 0,
        //"b1": 0
    },
    "disable": ["remeshing"],
    "implicit": false,
    "explicit_massdamping": 1e-1, // maybe even lower
    "explicit_stretchdamping": 1e-2, // stiffest term
    "frame_time": 0.04,
    "frame_steps": 400,
    "end_time": 10,
    "cloths": [{
        "mesh": "meshes/square.obj",
        "transform": {"scale": 0.1, "translate": [-0.05, -0.1, 0.2]},
        "materials": [{"data": "materials/gray-interlock.json",
                       "thicken": 2}]
    }],
    "motions": [[
        {"time": 0, "transform": {"translate": [0,0,0]}},
        {"time": 0.5, "transform": {"translate": [-0.05,0,0]}}
    ], [
        {"time": 0, "transform": {"translate": [0,0,0]}},
        {"time": 0.5, "transform": {"translate": [0.05,0,0]}}
    ]],
    "handles": [
      {"nodes": [3], "motion": 0},
      {"nodes": [2], "motion": 1},
      {"nodes": [0], "motion": 0},
      {"nodes": [1], "motion": 1}
    ],
    "gravity": [0, 0, -9.8],
    "magic": {"repulsion_thickness": 5e-3, "collision_stiffness": 1e6,
	      "relax_initial_state": false,
              "fixed_high_res_mesh": true}
}
